Metadata-Version: 2.1
Name: django-autotranslate2
Version: 1.2.7
Summary: A simple Django app to automatically translate the pot (`.po`) files generated by django's makemessages command using google translate.
Home-page: https://github.com/achillis2/django-autotranslate2
Author: Ding Li
Author-email: dingli@gmail.com
License: MIT License
Classifier: Environment :: Web Environment
Classifier: Framework :: Django
Classifier: Development Status :: 5 - Production/Stable
Classifier: Intended Audience :: Developers
Classifier: License :: OSI Approved :: MIT License
Classifier: Natural Language :: English
Classifier: Programming Language :: Python
Classifier: Programming Language :: Python :: 3
Classifier: Topic :: Internet :: WWW/HTTP
Classifier: Topic :: Internet :: WWW/HTTP :: Dynamic Content
Classifier: Topic :: Software Development :: Libraries :: Python Modules
License-File: LICENSE
Requires-Dist: django
Requires-Dist: googletrans ==3.1.0a0
Requires-Dist: polib
Requires-Dist: six
